ddbc/__init__.py
ddbc/cache.py
ddbc/init.py
ddbc/utils.py
ddbc-0.1.0.dist-info/DESCRIPTION.rst
ddbc-0.1.0.dist-info/METADATA
ddbc-0.1.0.dist-info/RECORD
ddbc-0.1.0.dist-info/WHEEL
ddbc-0.1.0.dist-info/metadata.json
ddbc-0.1.0.dist-info/top_level.txt
